sparkplug_images/__init__.py
sparkplug_images/apps.py
sparkplug_images/enums/__init__.py
sparkplug_images/enums/client.py
sparkplug_images/fields/__init__.py
sparkplug_images/fields/image.py
sparkplug_images/migrations/0001_initial.py
sparkplug_images/migrations/0002_auto_20210607_2228.py
sparkplug_images/migrations/__init__.py
sparkplug_images/models/__init__.py
sparkplug_images/models/image.py
sparkplug_images/permissions/__init__.py
sparkplug_images/permissions/image.py
sparkplug_images/serializers/__init__.py
sparkplug_images/serializers/image_expanded.py
sparkplug_images/serializers/image_teaser.py
sparkplug_images/serializers/image_write.py
sparkplug_images/services/__init__.py
sparkplug_images/services/optimize_image.py
sparkplug_images/signals.py
sparkplug_images/tasks/__init__.py
sparkplug_images/tasks/process_image.py
sparkplug_images/uploads.py
sparkplug_images/urls.py
sparkplug_images/views/__init__.py
sparkplug_images/views/image.py
sparkplug_api_images-1.0.5.dist-info/METADATA
sparkplug_api_images-1.0.5.dist-info/WHEEL
sparkplug_api_images-1.0.5.dist-info/RECORD
