Metadata-Version: 2.3
Name: sparkplug-api-images
Version: 1.0.5
Summary: Image package for Sparkplug apps
License: MIT
Author: Sparkplug Marcus
Author-email: sparkplugmarcus@gmail.com
Requires-Python: >=3.10,<4.0
Classifier: License :: OSI Approved :: MIT License
Classifier: Programming Language :: Python :: 3
Classifier: Programming Language :: Python :: 3.10
Classifier: Programming Language :: Python :: 3.11
Classifier: Programming Language :: Python :: 3.12
Classifier: Programming Language :: Python :: 3.13
Requires-Dist: Pillow (>=10.0.0,<10.1.0)
Requires-Dist: sorl-thumbnail (>=12.10.0,<12.11.0)
Requires-Dist: sparkplug-api-core (>=1.0.6,<1.1.0)
